elusion/__init__.py
elusion/py.typed
elusion/_core/__init__.py
elusion/_core/authentication.py
elusion/_core/base_client.py
elusion/_core/base_exceptions.py
elusion/_core/base_models.py
elusion/_core/configuration.py
elusion/_core/http_client.py
elusion/_core/retry_handler.py
elusion/_core/types.py
elusion_kit-0.0.4.dist-info/METADATA
elusion_kit-0.0.4.dist-info/WHEEL
elusion_kit-0.0.4.dist-info/RECORD
